{
	"version": "6",
	"dialect": "sqlite",
	"id": "4a4cd597-b79c-4efe-97dc-2266ac5afcf9",
	"prevId": "e0f9fbe4-ed3d-4cbd-be01-da6e5475d481",
	"tables": {
		"account": {
			"name": "account",
			"columns": {
				"id": {
					"name": "id",
					"type": "text",
					"primaryKey": true,
					"notNull": true,
					"autoincrement": false
				},
				"account_id": {
					"name": "account_id",
					"type": "text",
					"primaryKey": false,
					"notNull": true,
					"autoincrement": false
				},
				"provider_id": {
					"name": "provider_id",
					"type": "text",
					"primaryKey": false,
					"notNull": true,
					"autoincrement": false
				},
				"user_id": {
					"name": "user_id",
					"type": "text",
					"primaryKey": false,
					"notNull": true,
					"autoincrement": false
				},
				"access_token": {
					"name": "access_token",
					"type": "text",
					"primaryKey": false,
					"notNull": false,
					"autoincrement": false
				},
				"refresh_token": {
					"name": "refresh_token",
					"type": "text",
					"primaryKey": false,
					"notNull": false,
					"autoincrement": false
				},
				"id_token": {
					"name": "id_token",
					"type": "text",
					"primaryKey": false,
					"notNull": false,
					"autoincrement": false
				},
				"access_token_expires_at": {
					"name": "access_token_expires_at",
					"type": "integer",
					"primaryKey": false,
					"notNull": false,
					"autoincrement": false
				},
				"refresh_token_expires_at": {
					"name": "refresh_token_expires_at",
					"type": "integer",
					"primaryKey": false,
					"notNull": false,
					"autoincrement": false
				},
				"scope": {
					"name": "scope",
					"type": "text",
					"primaryKey": false,
					"notNull": false,
					"autoincrement": false
				},
				"password": {
					"name": "password",
					"type": "text",
					"primaryKey": false,
					"notNull": false,
					"autoincrement": false
				},
				"created_at": {
					"name": "created_at",
					"type": "integer",
					"primaryKey": false,
					"notNull": true,
					"autoincrement": false
				},
				"updated_at": {
					"name": "updated_at",
					"type": "integer",
					"primaryKey": false,
					"notNull": true,
					"autoincrement": false
				}
			},
			"indexes": {},
			"foreignKeys": {
				"account_user_id_user_id_fk": {
					"name": "account_user_id_user_id_fk",
					"tableFrom": "account",
					"tableTo": "user",
					"columnsFrom": ["user_id"],
					"columnsTo": ["id"],
					"onDelete": "no action",
					"onUpdate": "no action"
				}
			},
			"compositePrimaryKeys": {},
			"uniqueConstraints": {},
			"checkConstraints": {}
		},
		"session": {
			"name": "session",
			"columns": {
				"id": {
					"name": "id",
					"type": "text",
					"primaryKey": true,
					"notNull": true,
					"autoincrement": false
				},
				"expires_at": {
					"name": "expires_at",
					"type": "integer",
					"primaryKey": false,
					"notNull": true,
					"autoincrement": false
				},
				"token": {
					"name": "token",
					"type": "text",
					"primaryKey": false,
					"notNull": true,
					"autoincrement": false
				},
				"created_at": {
					"name": "created_at",
					"type": "integer",
					"primaryKey": false,
					"notNull": true,
					"autoincrement": false
				},
				"updated_at": {
					"name": "updated_at",
					"type": "integer",
					"primaryKey": false,
					"notNull": true,
					"autoincrement": false
				},
				"ip_address": {
					"name": "ip_address",
					"type": "text",
					"primaryKey": false,
					"notNull": false,
					"autoincrement": false
				},
				"user_agent": {
					"name": "user_agent",
					"type": "text",
					"primaryKey": false,
					"notNull": false,
					"autoincrement": false
				},
				"user_id": {
					"name": "user_id",
					"type": "text",
					"primaryKey": false,
					"notNull": true,
					"autoincrement": false
				}
			},
			"indexes": {
				"session_token_unique": {
					"name": "session_token_unique",
					"columns": ["token"],
					"isUnique": true
				}
			},
			"foreignKeys": {
				"session_user_id_user_id_fk": {
					"name": "session_user_id_user_id_fk",
					"tableFrom": "session",
					"tableTo": "user",
					"columnsFrom": ["user_id"],
					"columnsTo": ["id"],
					"onDelete": "no action",
					"onUpdate": "no action"
				}
			},
			"compositePrimaryKeys": {},
			"uniqueConstraints": {},
			"checkConstraints": {}
		},
		"user": {
			"name": "user",
			"columns": {
				"id": {
					"name": "id",
					"type": "text",
					"primaryKey": true,
					"notNull": true,
					"autoincrement": false
				},
				"name": {
					"name": "name",
					"type": "text",
					"primaryKey": false,
					"notNull": true,
					"autoincrement": false
				},
				"email": {
					"name": "email",
					"type": "text",
					"primaryKey": false,
					"notNull": true,
					"autoincrement": false
				},
				"email_verified": {
					"name": "email_verified",
					"type": "integer",
					"primaryKey": false,
					"notNull": true,
					"autoincrement": false
				},
				"image": {
					"name": "image",
					"type": "text",
					"primaryKey": false,
					"notNull": false,
					"autoincrement": false
				},
				"created_at": {
					"name": "created_at",
					"type": "integer",
					"primaryKey": false,
					"notNull": true,
					"autoincrement": false
				},
				"updated_at": {
					"name": "updated_at",
					"type": "integer",
					"primaryKey": false,
					"notNull": true,
					"autoincrement": false
				}
			},
			"indexes": {
				"user_email_unique": {
					"name": "user_email_unique",
					"columns": ["email"],
					"isUnique": true
				}
			},
			"foreignKeys": {},
			"compositePrimaryKeys": {},
			"uniqueConstraints": {},
			"checkConstraints": {}
		},
		"verification": {
			"name": "verification",
			"columns": {
				"id": {
					"name": "id",
					"type": "text",
					"primaryKey": true,
					"notNull": true,
					"autoincrement": false
				},
				"identifier": {
					"name": "identifier",
					"type": "text",
					"primaryKey": false,
					"notNull": true,
					"autoincrement": false
				},
				"value": {
					"name": "value",
					"type": "text",
					"primaryKey": false,
					"notNull": true,
					"autoincrement": false
				},
				"expires_at": {
					"name": "expires_at",
					"type": "integer",
					"primaryKey": false,
					"notNull": true,
					"autoincrement": false
				},
				"created_at": {
					"name": "created_at",
					"type": "integer",
					"primaryKey": false,
					"notNull": false,
					"autoincrement": false
				},
				"updated_at": {
					"name": "updated_at",
					"type": "integer",
					"primaryKey": false,
					"notNull": false,
					"autoincrement": false
				}
			},
			"indexes": {},
			"foreignKeys": {},
			"compositePrimaryKeys": {},
			"uniqueConstraints": {},
			"checkConstraints": {}
		},
		"bills": {
			"name": "bills",
			"columns": {
				"id": {
					"name": "id",
					"type": "integer",
					"primaryKey": true,
					"notNull": true,
					"autoincrement": true
				},
				"biller_name": {
					"name": "biller_name",
					"type": "text",
					"primaryKey": false,
					"notNull": true,
					"autoincrement": false
				},
				"total_amount": {
					"name": "total_amount",
					"type": "real",
					"primaryKey": false,
					"notNull": true,
					"autoincrement": false
				},
				"due_date": {
					"name": "due_date",
					"type": "integer",
					"primaryKey": false,
					"notNull": true,
					"autoincrement": false
				},
				"status": {
					"name": "status",
					"type": "text",
					"primaryKey": false,
					"notNull": true,
					"autoincrement": false,
					"default": "'pending'"
				},
				"pdf_url": {
					"name": "pdf_url",
					"type": "text",
					"primaryKey": false,
					"notNull": false,
					"autoincrement": false
				},
				"created_at": {
					"name": "created_at",
					"type": "integer",
					"primaryKey": false,
					"notNull": true,
					"autoincrement": false
				},
				"updated_at": {
					"name": "updated_at",
					"type": "integer",
					"primaryKey": false,
					"notNull": true,
					"autoincrement": false
				}
			},
			"indexes": {},
			"foreignKeys": {},
			"compositePrimaryKeys": {},
			"uniqueConstraints": {},
			"checkConstraints": {}
		},
		"debts": {
			"name": "debts",
			"columns": {
				"id": {
					"name": "id",
					"type": "integer",
					"primaryKey": true,
					"notNull": true,
					"autoincrement": true
				},
				"bill_id": {
					"name": "bill_id",
					"type": "integer",
					"primaryKey": false,
					"notNull": true,
					"autoincrement": false
				},
				"housemate_id": {
					"name": "housemate_id",
					"type": "integer",
					"primaryKey": false,
					"notNull": true,
					"autoincrement": false
				},
				"amount_owed": {
					"name": "amount_owed",
					"type": "real",
					"primaryKey": false,
					"notNull": true,
					"autoincrement": false
				},
				"is_paid": {
					"name": "is_paid",
					"type": "integer",
					"primaryKey": false,
					"notNull": true,
					"autoincrement": false,
					"default": false
				},
				"paid_at": {
					"name": "paid_at",
					"type": "integer",
					"primaryKey": false,
					"notNull": false,
					"autoincrement": false
				},
				"created_at": {
					"name": "created_at",
					"type": "integer",
					"primaryKey": false,
					"notNull": true,
					"autoincrement": false
				},
				"updated_at": {
					"name": "updated_at",
					"type": "integer",
					"primaryKey": false,
					"notNull": true,
					"autoincrement": false
				}
			},
			"indexes": {},
			"foreignKeys": {
				"debts_bill_id_bills_id_fk": {
					"name": "debts_bill_id_bills_id_fk",
					"tableFrom": "debts",
					"tableTo": "bills",
					"columnsFrom": ["bill_id"],
					"columnsTo": ["id"],
					"onDelete": "cascade",
					"onUpdate": "no action"
				},
				"debts_housemate_id_housemates_id_fk": {
					"name": "debts_housemate_id_housemates_id_fk",
					"tableFrom": "debts",
					"tableTo": "housemates",
					"columnsFrom": ["housemate_id"],
					"columnsTo": ["id"],
					"onDelete": "cascade",
					"onUpdate": "no action"
				}
			},
			"compositePrimaryKeys": {},
			"uniqueConstraints": {},
			"checkConstraints": {}
		},
		"housemates": {
			"name": "housemates",
			"columns": {
				"id": {
					"name": "id",
					"type": "integer",
					"primaryKey": true,
					"notNull": true,
					"autoincrement": true
				},
				"name": {
					"name": "name",
					"type": "text",
					"primaryKey": false,
					"notNull": true,
					"autoincrement": false
				},
				"email": {
					"name": "email",
					"type": "text",
					"primaryKey": false,
					"notNull": false,
					"autoincrement": false
				},
				"bank_alias": {
					"name": "bank_alias",
					"type": "text",
					"primaryKey": false,
					"notNull": false,
					"autoincrement": false
				},
				"is_active": {
					"name": "is_active",
					"type": "integer",
					"primaryKey": false,
					"notNull": true,
					"autoincrement": false,
					"default": true
				},
				"created_at": {
					"name": "created_at",
					"type": "integer",
					"primaryKey": false,
					"notNull": true,
					"autoincrement": false
				},
				"updated_at": {
					"name": "updated_at",
					"type": "integer",
					"primaryKey": false,
					"notNull": true,
					"autoincrement": false
				}
			},
			"indexes": {
				"housemates_email_unique": {
					"name": "housemates_email_unique",
					"columns": ["email"],
					"isUnique": true
				}
			},
			"foreignKeys": {},
			"compositePrimaryKeys": {},
			"uniqueConstraints": {},
			"checkConstraints": {}
		},
		"todo": {
			"name": "todo",
			"columns": {
				"id": {
					"name": "id",
					"type": "integer",
					"primaryKey": true,
					"notNull": true,
					"autoincrement": true
				},
				"text": {
					"name": "text",
					"type": "text",
					"primaryKey": false,
					"notNull": true,
					"autoincrement": false
				},
				"completed": {
					"name": "completed",
					"type": "integer",
					"primaryKey": false,
					"notNull": true,
					"autoincrement": false,
					"default": false
				}
			},
			"indexes": {},
			"foreignKeys": {},
			"compositePrimaryKeys": {},
			"uniqueConstraints": {},
			"checkConstraints": {}
		},
		"unreconciled_transactions": {
			"name": "unreconciled_transactions",
			"columns": {
				"id": {
					"name": "id",
					"type": "integer",
					"primaryKey": true,
					"notNull": true,
					"autoincrement": true
				},
				"transaction_id": {
					"name": "transaction_id",
					"type": "text",
					"primaryKey": false,
					"notNull": true,
					"autoincrement": false
				},
				"description": {
					"name": "description",
					"type": "text",
					"primaryKey": false,
					"notNull": true,
					"autoincrement": false
				},
				"amount": {
					"name": "amount",
					"type": "real",
					"primaryKey": false,
					"notNull": true,
					"autoincrement": false
				},
				"reason": {
					"name": "reason",
					"type": "text",
					"primaryKey": false,
					"notNull": true,
					"autoincrement": false
				},
				"raw_data": {
					"name": "raw_data",
					"type": "text",
					"primaryKey": false,
					"notNull": false,
					"autoincrement": false
				},
				"created_at": {
					"name": "created_at",
					"type": "integer",
					"primaryKey": false,
					"notNull": true,
					"autoincrement": false
				}
			},
			"indexes": {
				"unreconciled_transactions_transaction_id_unique": {
					"name": "unreconciled_transactions_transaction_id_unique",
					"columns": ["transaction_id"],
					"isUnique": true
				}
			},
			"foreignKeys": {},
			"compositePrimaryKeys": {},
			"uniqueConstraints": {},
			"checkConstraints": {}
		}
	},
	"views": {},
	"enums": {},
	"_meta": {
		"schemas": {},
		"tables": {},
		"columns": {}
	},
	"internal": {
		"indexes": {}
	}
}
